brainthon/__init__.py
brainthon/modulo1.py
brainthon/modulo2.py
brainthon/utils.py
tests/__init__.py
tests/test_modulo1.py
tests/test_modulo2.py
sua_biblioteca-0.1.0.dist-info/LICENSE
sua_biblioteca-0.1.0.dist-info/METADATA
sua_biblioteca-0.1.0.dist-info/WHEEL
sua_biblioteca-0.1.0.dist-info/top_level.txt
sua_biblioteca-0.1.0.dist-info/RECORD
