Metadata-Version: 2.1
Name: sua_biblioteca
Version: 0.1.0
Summary: Uma biblioteca simples para operações matemáticas básicas.
Home-page: https://github.com/seu_usuario/sua_biblioteca
Author: Seu Nome
Author-email: seuemail@exemplo.com
Classifier: Programming Language :: Python :: 3
Classifier: License :: OSI Approved :: MIT License
Classifier: Operating System :: OS Independent
Requires-Python: >=3.6
License-File: LICENSE
